[
  {
    "term": "Vesta",
    "slug": "vesta",
    "category": "plan\u00e8te",
    "short": "Ast\u00e9ro\u00efde de la d\u00e9votion, du foyer int\u00e9rieur et du focus.",
    "body": "Vesta symbolise le feu sacr\u00e9, le d\u00e9vouement \u00e0 une cause ou \u00e0 une pratique. Elle repr\u00e9sente la capacit\u00e9 de se concentrer intens\u00e9ment sur un objectif en sacrifiant parfois les plaisirs personnels. Elle est li\u00e9e \u00e0 la puret\u00e9 d\u2019intention et au travail solitaire.",
    "related": ["Travail", "Spirituel", "Concentration"]
  },
  {
    "term": "Vicieux (aspect)",
    "slug": "vicieux-aspect",
    "category": "aspect",
    "short": "Terme ancien désignant un aspect considéré comme particulièrement difficile ou pernicieux.",
    "body": "En astrologie classique, le terme « vicieux » qualifiait certains aspects jugés particulièrement néfastes, notamment le carré et l'opposition impliquant des maléfiques traditionnels (Mars, Saturne). L'expression « aspect vicieux » suggérait une influence corrompue, difficile à canaliser, produisant des effets nuisibles récurrents. Cette terminologie reflète une vision déterministe de l'astrologie qui n'a plus cours dans la pratique moderne. Aujourd'hui, on préfère parler d'aspects tendus, dissonants ou dynamiques, reconnaissant que même les configurations les plus difficiles peuvent être transformées en forces par la conscience et le travail sur soi. Le terme reste utile pour comprendre les textes astrologiques anciens, où la distinction entre aspects « bénéfiques » et « vicieux » structurait toute l'interprétation.",
    "related": ["Carré", "Opposition", "Dissonance", "Aspect"]
  }
]
